crossconfig/__init__.py
crossconfig/classes.py
crossconfig-0.0.1.dist-info/METADATA
crossconfig-0.0.1.dist-info/WHEEL
crossconfig-0.0.1.dist-info/RECORD
