Metadata-Version: 2.4
Name: crossconfig
Version: 0.0.1
Summary: Simple cross-platform settings/configuration package.
Project-URL: Homepage, https://github.com/k98kurz/crossconfig
Project-URL: Bug Tracker, https://github.com/k98kurz/crossconfig/issues
Author-email: k98kurz <k98kurz@gmail.com>
Classifier: Development Status :: 3 - Alpha
Classifier: License :: OSI Approved :: ISC License (ISCL)
Classifier: Operating System :: OS Independent
Classifier: Programming Language :: Python :: 3
Classifier: Topic :: Other/Nonlisted Topic
Requires-Python: >=3.10
